molecule_digitalocean/__init__.py
molecule_digitalocean/driver.py
molecule_digitalocean/cookiecutter/scenario/driver/digitalocean/cookiecutter.json
molecule_digitalocean/cookiecutter/scenario/driver/digitalocean/{{cookiecutter.molecule_directory}}/{{cookiecutter.scenario_name}}/INSTALL.rst
molecule_digitalocean/cookiecutter/scenario/driver/digitalocean/{{cookiecutter.molecule_directory}}/{{cookiecutter.scenario_name}}/create.yml
molecule_digitalocean/cookiecutter/scenario/driver/digitalocean/{{cookiecutter.molecule_directory}}/{{cookiecutter.scenario_name}}/destroy.yml
molecule_digitalocean/cookiecutter/scenario/driver/digitalocean/{{cookiecutter.molecule_directory}}/{{cookiecutter.scenario_name}}/playbook.yml
molecule_digitalocean/cookiecutter/scenario/driver/digitalocean/{{cookiecutter.molecule_directory}}/{{cookiecutter.scenario_name}}/prepare.yml
molecule_digitalocean/test/__init__.py
molecule_digitalocean/test/scenarios/driver/digitalocean/molecule/default/molecule.yml
molecule_digitalocean/test/scenarios/driver/digitalocean/molecule/default/playbook.yml
molecule_digitalocean/test/scenarios/driver/digitalocean/molecule/default/tests/test_default.py
molecule_digitalocean/test/scenarios/driver/digitalocean/molecule/multi-node/molecule.yml
molecule_digitalocean/test/scenarios/driver/digitalocean/molecule/multi-node/playbook.yml
molecule_digitalocean/test/scenarios/driver/digitalocean/molecule/multi-node/tests/test_default.py
molecule_digitalocean/test/unit/__init__.py
molecule_digitalocean/test/unit/driver/__init__.py
molecule_digitalocean/test/unit/driver/test_digitalocean.py
molecule_digitalocean-0.1.dist-info/LICENSE
molecule_digitalocean-0.1.dist-info/METADATA
molecule_digitalocean-0.1.dist-info/WHEEL
molecule_digitalocean-0.1.dist-info/entry_points.txt
molecule_digitalocean-0.1.dist-info/top_level.txt
molecule_digitalocean-0.1.dist-info/RECORD
