Metadata-Version: 2.1
Name: molecule-digitalocean
Version: 0.1
Summary: digitalocean Molecule Plugin :: run molecule tests on digitalocean
Home-page: https://github.com/pycontribs/molecule-digitalocean
Author: Sorin Sbarnea
Author-email: sorin.sbarnea@gmail.com
Maintainer: Sorin Sbarnea
Maintainer-email: sorin.sbarnea@gmail.com
License: MIT
Project-URL: Bug Tracker, https://github.com/pycontribs/molecule-digitalocean/issues
Project-URL: Release Management, https://github.com/pycontribs/molecule-digitalocean/projects
Project-URL: CI: Travis, https://travis-ci.com/pycontribs/molecule-digitalocean
Project-URL: Source Code, https://github.com/pycontribs/molecule-digitalocean
Keywords: ansible,roles,testing,molecule,plugin,digitalocean
Platform: UNKNOWN
Classifier: Development Status :: 5 - Production/Stable
Classifier: Environment :: Console
Classifier: Framework :: Pytest
Classifier: Intended Audience :: Developers
Classifier: Intended Audience :: Information Technology
Classifier: Intended Audience :: System Administrators
Classifier: License :: OSI Approved :: MIT License
Classifier: Natural Language :: English
Classifier: Operating System :: OS Independent
Classifier: Programming Language :: Python :: 2
Classifier: Programming Language :: Python :: 2.7
Classifier: Programming Language :: Python :: 3
Classifier: Programming Language :: Python :: 3.5
Classifier: Programming Language :: Python :: 3.6
Classifier: Programming Language :: Python :: 3.7
Classifier: Topic :: System :: Systems Administration
Classifier: Topic :: Utilities
Requires-Python: !=3.0.*,!=3.1.*,!=3.2.*,!=3.3.*,!=3.4.*,>=2.7
Requires-Dist: molecule (>=3.0a0)
Requires-Dist: pyyaml (<6,>=5.1)
Requires-Dist: dopy ; python_version < "3.0"
Provides-Extra: test
Requires-Dist: flake8 (<4,>=3.6.0) ; extra == 'test'
Requires-Dist: mock (<4,>=3.0.5) ; extra == 'test'
Requires-Dist: pytest (<5,>=4.6.3) ; extra == 'test'
Requires-Dist: pytest-cov (<3,>=2.7.1) ; extra == 'test'
Requires-Dist: pytest-helpers-namespace (<2020,>=2019.1.8) ; extra == 'test'
Requires-Dist: pytest-mock (<2,>=1.10.4) ; extra == 'test'
Requires-Dist: pytest-verbose-parametrize (<2,>=1.7.0) ; extra == 'test'
Requires-Dist: pytest-xdist (<2,>=1.29.0) ; extra == 'test'
Requires-Dist: pytest-dependency ; extra == 'test'
